2007/lcd_ctrl.v
module LCD_CTRL(clk, reset, datain, cmd, cmd_valid, dataout, output_valid, busy);
input           clk;
input           reset;
input   [7:0]   datain;
input   [2:0]   cmd;
input           cmd_valid;
output  reg[7:0]   dataout;
output  reg       output_valid;
output  reg        busy;

reg [1:0]state, next_state;

parameter READ_OP = 2'd0,
		  READ = 2'd1,
		  CAL = 2'd2,
		  OUT = 2'd3;

parameter REFLASH = 3'd0,
		  LOADDATA = 3'd1,
		  ZOOMIN = 3'd2,
		  ZOOMOUT = 3'd3,
		  SHIFT_RIGHT = 3'd4,
		  SHIFT_LEFT = 3'd5,
		  SHIFT_UP = 3'd6,
		  SHIFT_DOWN = 3'd7;
		  

reg [7:0] data_in[0:63];
reg [5:0] counter;
reg [2:0] pos_x, pos_y;
reg magnifi;
wire [5:0]pos;

assign pos = {pos_y, pos_x};
integer i;

always@(posedge clk or posedge reset)begin
    if(reset)
        state <= READ_OP;
    else 
        state <= next_state;
end

always@(*)begin
    if(reset)
        next_state = READ_OP;
    else begin
        case(state)
			READ_OP: begin
				if(cmd == LOADDATA) next_state = READ;
				else if(cmd == REFLASH) next_state = OUT;
				else next_state = CAL;
			end
			READ: begin
				if(counter == 63) next_state = OUT;
				else next_state = READ;
			end
			CAL: next_state = OUT;
			OUT: begin
				if(counter == 16) next_state = READ_OP;
				else next_state = OUT;
			end
            default: next_state = READ_OP;
        endcase
    end 
end


//DATA INPUT
always@(posedge clk or posedge reset)begin
    if(reset)begin
		for(i=0;i<64;i=i+1)
			data_in[i] <= 5;
		// busy <= 0;
		pos_x <= 2;
		pos_y <= 2;
		counter <= 0;
		magnifi <= 0;
    end
    else begin
		if(state == READ) begin
			data_in[counter] <= datain;
			counter <= counter + 1;
			magnifi <= 0;
			// busy <= 1;
		end
		else if(next_state == CAL) begin
			case(cmd)
				ZOOMIN:begin
					magnifi <= 1;
					pos_x <= 2;
					pos_y <= 2;
				end
				ZOOMOUT:begin
					magnifi <= 0;
				end
				SHIFT_RIGHT:begin
					if(pos_x < 4)
						pos_x <= pos_x + 1;
					else 
						pos_x <= pos_x;
				end
				SHIFT_LEFT:begin
					if(pos_x > 0)
						pos_x <= pos_x - 1;
					else 
						pos_x <= pos_x;
				end

				SHIFT_UP:begin
					if(pos_y > 0)
						pos_y <= pos_y - 1;
					else 
						pos_y <= pos_y;
				end
				SHIFT_DOWN:begin
					if(pos_y < 4)
						pos_y <= pos_y + 1;
					else 
						pos_y <= pos_y;
				end
				default:begin
					pos_x <= pos_x;
					pos_y <= pos_y;
				end
			endcase
			// busy <= 1;
		end
		else if(state == OUT)begin
			if(magnifi == 0)begin
				case(counter)
					0:	dataout <= data_in[0];
					1:	dataout <= data_in[2];
					2:  dataout <= data_in[4];
					3:  dataout <= data_in[6];
					4:  dataout <= data_in[16];
					5:  dataout <= data_in[18];
					6:  dataout <= data_in[20];
					7:  dataout <= data_in[22];
					8:  dataout <= data_in[32];
					9:  dataout <= data_in[34];
					10: dataout <= data_in[36];
					11: dataout <= data_in[38];
					12: dataout <= data_in[48];
					13: dataout <= data_in[50];
					14: dataout <= data_in[52];
					15: dataout <= data_in[54];
					
				endcase
			end
			else begin
				case(counter)
					0:	dataout <= data_in[pos];
					1:	dataout <= data_in[pos+1];
					2:  dataout <= data_in[pos+2];
					3:  dataout <= data_in[pos+3];
					4:  dataout <= data_in[pos+8];
					5:  dataout <= data_in[pos+9];
					6:  dataout <= data_in[pos+10];
					7:  dataout <= data_in[pos+11];
					8:  dataout <= data_in[pos+16];
					9:  dataout <= data_in[pos+17];
					10: dataout <= data_in[pos+18];
					11: dataout <= data_in[pos+19];
					12: dataout <= data_in[pos+24];
					13: dataout <= data_in[pos+25];
					14: dataout <= data_in[pos+26];
					15: dataout <= data_in[pos+27];
				endcase
			end
			if(counter == 16)begin
			 	// busy <= 0;
				output_valid <= 0;
				counter <= 0;
			end
			else begin
				// busy <= 1;
				output_valid <= 1;
				counter <= counter + 1;
			end
			
		end
		else counter <= 0;
    end
end

always @(posedge clk or posedge reset) begin
	if(reset)
		busy <= 0;
	else begin
		if(counter == 16 && state == OUT)
			busy <= 0;
		else 
			busy <= 1;
	end
end

endmodule

2007/testfixture.v
`timescale 1ns/10ps
`define CYCLE    100           	        // Modify your clock period here
`define SDFFILE  "./lcd_ctrl.sdf"	// Modify your sdf file name
`define IMAGE    "./image2.dat"         // Modify your test image file: image1.dat or image2.dat
`define CMD      "./cmd2.dat"           // Modify your test cmd file: cmd1.dat or cmd2.dat
`define EXPECT   "./out_golden2.dat"    // Modify your output golden file: out_golden1.dat or out_golden2.dat

module test;
parameter IMAGE_N_PAT = 64;
parameter CMD_N_PAT = 45;
parameter OUT_LENGTH= 720;
parameter t_reset = `CYCLE*2;

reg           clk;
reg           reset;
reg   [7:0]   datain;
reg   [2:0]   cmd;
reg           cmd_valid;
wire  [7:0]   dataout;
wire          output_valid;
wire          busy;

reg   [7:0]   image_mem [0:IMAGE_N_PAT-1];
reg   [2:0]   cmd_mem   [0:CMD_N_PAT-1];
reg   [7:0]   out_mem   [0:OUT_LENGTH-1];
reg   [7:0]   out_temp;

reg           stop;
integer       i, j, out_f, err, pattern_num;
reg           over;

   LCD_CTRL top(.clk(clk), .reset(reset), .datain(datain), 
                .cmd(cmd), .cmd_valid(cmd_valid), .dataout(dataout), 
                .output_valid(output_valid), .busy(busy));          
   


//initial $sdf_annotate(`SDFFILE, top);

initial	$readmemh (`IMAGE,  image_mem);
initial	$readmemh (`CMD,    cmd_mem);
initial	$readmemh (`EXPECT, out_mem);

initial begin
   clk         = 1'b0;
   reset       = 1'b0;
   cmd_valid   = 1'b0;
   stop        = 1'b0;  
   over        = 1'b0;
   pattern_num = 0;
   err         = 0;    
end

always begin #(`CYCLE/2) clk = ~clk; end

initial begin
$dumpfile("LCD_CTRL.vcd");
$dumpvars;
//$fsdbDumpfile("LCD_CTRL.fsdb");
//$fsdbDumpvars;

   out_f = $fopen("out.dat");
   if (out_f == 0) begin
        $display("Output file open error !");
        $finish;
   end
end


initial begin
   @(negedge clk)  reset = 1'b1;
   #t_reset        reset = 1'b0;
   
   @(negedge clk)    i=0;
   while (i <= CMD_N_PAT) begin               
      if(!busy) begin
        cmd = cmd_mem[i];
        cmd_valid = 1'b1;  
        
        if(cmd_mem[i] === 3'h1) begin    //cmd: Load data        
           for(j=0; j<=IMAGE_N_PAT; j=j+1)begin
              @(negedge clk) datain = image_mem[j];
                             cmd = 'hz; cmd_valid = 1'b0;
           end
           i = i+1;
        end
        else begin                      //cmd: other command
           @(negedge clk) datain='hz; cmd_valid = 1'b0; i = i+1;
        end       
      end 
      else begin
         datain='hz; cmd = 'hz;  cmd_valid = 0;
         @(negedge clk);
      end               
    end                                       
    stop = 1 ;      
end

always @(posedge clk)begin
   out_temp = out_mem[pattern_num];
   if(output_valid)begin
      $fdisplay(out_f,"%h", dataout);
      if(dataout !== out_temp) begin
         $display("ERROR at %d:output %h !=expect %h ",pattern_num, dataout, out_temp);
         err = err + 1 ;
      end
      pattern_num = pattern_num + 1;      
   end
   if(pattern_num === OUT_LENGTH)  over = 1'b1;
end


initial begin
      @(posedge stop)      
      if((over) || (pattern_num!='h0)) begin
         $display("---------------------------------------------\n");
         if (err == 0)  begin
            $display("All data have been generated successfully!\n");
            $display("-------------------PASS-------------------\n");
         end
         else 
            $display("There are %d errors!\n", err);
            $display("---------------------------------------------\n");
      end
      else begin
        $display("---------------------------------------------\n");
        $display("Error!!! There is no any data output ...!\n");
        $display("-------------------FAIL-------------------\n");
        $display("---------------------------------------------\n");
      end
      $finish;
end
   
endmodule

2007/LCD_CTRL.vcd
$date
	Sat Jan 21 01:08:26 2023
$end
$version
	ModelSim Version 10.1d
$end
$timescale
	10ps
$end
$scope module test $end
$var parameter 32 ! IMAGE_N_PAT $end
$var parameter 32 " CMD_N_PAT $end
$var parameter 32 # OUT_LENGTH $end
$var parameter 32 $ t_reset $end
$var reg 1 % clk $end
$var reg 1 & reset $end
$var reg 8 ' datain [7:0] $end
$var reg 3 ( cmd [2:0] $end
$var reg 1 ) cmd_valid $end
$var wire 1 * dataout [7] $end
$var wire 1 + dataout [6] $end
$var wire 1 , dataout [5] $end
$var wire 1 - dataout [4] $end
$var wire 1 . dataout [3] $end
$var wire 1 / dataout [2] $end
$var wire 1 0 dataout [1] $end
$var wire 1 1 dataout [0] $end
$var wire 1 2 output_valid $end
$var wire 1 3 busy $end
$var reg 8 4 out_temp [7:0] $end
$var reg 1 5 stop $end
$var integer 32 6 i $end
$var integer 32 7 j $end
$var integer 32 8 out_f $end
$var integer 32 9 err $end
$var integer 32 : pattern_num $end
$var reg 1 ; over $end
$scope module top $end
$var parameter 2 < READ_OP $end
$var parameter 2 = READ $end
$var parameter 2 > CAL $end
$var parameter 2 ? OUT $end
$var parameter 3 @ REFLASH $end
$var parameter 3 A LOADDATA $end
$var parameter 3 B ZOOMIN $end
$var parameter 3 C ZOOMOUT $end
$var parameter 3 D SHIFT_RIGHT $end
$var parameter 3 E SHIFT_LEFT $end
$var parameter 3 F SHIFT_UP $end
$var parameter 3 G SHIFT_DOWN $end
$var wire 1 H clk $end
$var wire 1 I reset $end
$var wire 1 J datain [7] $end
$var wire 1 K datain [6] $end
$var wire 1 L datain [5] $end
$var wire 1 M datain [4] $end
$var wire 1 N datain [3] $end
$var wire 1 O datain [2] $end
$var wire 1 P datain [1] $end
$var wire 1 Q datain [0] $end
$var wire 1 R cmd [2] $end
$var wire 1 S cmd [1] $end
$var wire 1 T cmd [0] $end
$var wire 1 U cmd_valid $end
$var reg 8 V dataout [7:0] $end
$var reg 1 W output_valid $end
$var reg 1 X busy $end
$var reg 2 Y state [1:0] $end
$var reg 2 Z next_state [1:0] $end
$var reg 6 [ counter [5:0] $end
$var reg 3 \ pos_x [2:0] $end
$var reg 3 ] pos_y [2:0] $end
$var reg 1 ^ magnifi $end
$var wire 1 _ pos [5] $end
$var wire 1 ` pos [4] $end
$var wire 1 a pos [3] $end
$var wire 1 b pos [2] $end
$var wire 1 c pos [1] $end
$var wire 1 d pos [0] $end
$var integer 32 e i $end
$upscope $end
$upscope $end
$enddefinitions $end
#0
$dumpvars
0%
0&
bx '
bx (
0)
bx 4
05
0;
bx V
xW
xX
bx Y
b0 Z
bx [
bx \
bx ]
x^
b1000000 !
b101101 "
b1011010000 #
b11001000 $
b0 <
b1 =
b10 >
b11 ?
b0 @
b1 A
b10 B
b11 C
b100 D
b101 E
b110 F
b111 G
bx 6
bx 7
b10 8
b0 9
b0 :
bx e
x1
x0
x/
x.
x-
x,
x+
x*
x2
x3
xd
xc
xb
xa
x`
x_
0U
xT
xS
xR
xQ
xP
xO
xN
xM
xL
xK
xJ
0I
0H
$end
#5000
1%
1H
b11111111 4
b0 Y
b0 [
1X
13
b10 Z
#10000
0%
0H
1&
1I
b0 e
b1 e
b10 e
b11 e
b100 e
b101 e
b110 e
b111 e
b1000 e
b1001 e
b1010 e
b1011 e
b1100 e
b1101 e
b1110 e
b1111 e
b10000 e
b10001 e
b10010 e
b10011 e
b10100 e
b10101 e
b10110 e
b10111 e
b11000 e
b11001 e
b11010 e
b11011 e
b11100 e
b11101 e
b11110 e
b11111 e
b100000 e
b100001 e
b100010 e
b100011 e
b100100 e
b100101 e
b100110 e
b100111 e
b101000 e
b101001 e
b101010 e
b101011 e
b101100 e
b101101 e
b101110 e
b101111 e
b110000 e
b110001 e
b110010 e
b110011 e
b110100 e
b110101 e
b110110 e
b110111 e
b111000 e
b111001 e
b111010 e
b111011 e
b111100 e
b111101 e
b111110 e
b111111 e
b1000000 e
b0 Z
b10 \
b10 ]
0^
0X
0d
1c
0b
0a
1`
0_
03
#15000
1%
1H
b0 e
b1 e
b10 e
b11 e
b100 e
b101 e
b110 e
b111 e
b1000 e
b1001 e
b1010 e
b1011 e
b1100 e
b1101 e
b1110 e
b1111 e
b10000 e
b10001 e
b10010 e
b10011 e
b10100 e
b10101 e
b10110 e
b10111 e
b11000 e
b11001 e
b11010 e
b11011 e
b11100 e
b11101 e
b11110 e
b11111 e
b100000 e
b100001 e
b100010 e
b100011 e
b100100 e
b100101 e
b100110 e
b100111 e
b101000 e
b101001 e
b101010 e
b101011 e
b101100 e
b101101 e
b101110 e
b101111 e
b110000 e
b110001 e
b110010 e
b110011 e
b110100 e
b110101 e
b110110 e
b110111 e
b111000 e
b111001 e
b111010 e
b111011 e
b111100 e
b111101 e
b111110 e
b111111 e
b1000000 e
#20000
0%
0H
#25000
1%
1H
b0 e
b1 e
b10 e
b11 e
b100 e
b101 e
b110 e
b111 e
b1000 e
b1001 e
b1010 e
b1011 e
b1100 e
b1101 e
b1110 e
b1111 e
b10000 e
b10001 e
b10010 e
b10011 e
b10100 e
b10101 e
b10110 e
b10111 e
b11000 e
b11001 e
b11010 e
b11011 e
b11100 e
b11101 e
b11110 e
b11111 e
b100000 e
b100001 e
b100010 e
b100011 e
b100100 e
b100101 e
b100110 e
b100111 e
b101000 e
b101001 e
b101010 e
b101011 e
b101100 e
b101101 e
b101110 e
b101111 e
b110000 e
b110001 e
b110010 e
b110011 e
b110100 e
b110101 e
b110110 e
b110111 e
b111000 e
b111001 e
b111010 e
b111011 e
b111100 e
b111101 e
b111110 e
b111111 e
b1000000 e
#30000
0&
0%
0I
0H
b10 Z
b0 6
b1 (
1)
b0 7
1U
1T
0S
0R
b1 Z
#35000
1%
1H
b1 Y
1X
13
#40000
0%
0H
b11111111 '
bz (
0)
b1 7
1Q
1P
1O
1N
1M
1L
1K
1J
0U
zT
zS
zR
#45000
1%
1H
b1 [
#50000
0%
0H
b110110 '
b10 7
0Q
0N
0K
0J
#55000
1%
1H
b10 [
#60000
0%
0H
b11100111 '
b11 7
1Q
0M
1K
1J
#65000
1%
1H
b11 [
#70000
0%
0H
b11110000 '
b100 7
0Q
0P
0O
1M
#75000
1%
1H
b100 [
#80000
0%
0H
b1010101 '
b101 7
1Q
1O
0L
0J
#85000
1%
1H
b101 [
#90000
0%
0H
b110010 '
b110 7
0Q
1P
0O
1L
0K
#95000
1%
1H
b110 [
#100000
0%
0H
b1110101 '
b111 7
1Q
0P
1O
1K
#105000
1%
1H
b111 [
#110000
0%
0H
b1000010 '
b1000 7
0Q
1P
0O
0M
0L
#115000
1%
1H
b1000 [
#120000
0%
0H
b11000 '
b1001 7
0P
1N
1M
0K
#125000
1%
1H
b1001 [
#130000
0%
0H
b100000 '
b1010 7
0N
0M
1L
#135000
1%
1H
b1010 [
#140000
0%
0H
b1010111 '
b1011 7
1Q
1P
1O
1M
0L
1K
#145000
1%
1H
b1011 [
#150000
0%
0H
b110000 '
b1100 7
0Q
0P
0O
1L
0K
#155000
1%
1H
b1100 [
#160000
0%
0H
b11101011 '
b1101 7
1Q
1P
1N
0M
1K
1J
#165000
1%
1H
b1101 [
#170000
0%
0H
b10101111 '
b1110 7
1O
0K
#175000
1%
1H
b1110 [
#180000
0%
0H
b11101100 '
b1111 7
0Q
0P
1K
#185000
1%
1H
b1111 [
#190000
0%
0H
b10001 '
b10000 7
1Q
0O
0N
1M
0L
0K
0J
#195000
1%
1H
b10000 [
#200000
0%
0H
b1100001 '
b10001 7
0M
1L
1K
#205000
1%
1H
b10001 [
#210000
0%
0H
b1001001 '
b10010 7
1N
0L
#215000
1%
1H
b10010 [
#220000
0%
0H
b10010011 '
b10011 7
1P
0N
1M
0K
1J
#225000
1%
1H
b10011 [
#230000
0%
0H
b100010 '
b10100 7
0Q
0M
1L
0J
#235000
1%
1H
b10100 [
#240000
0%
0H
b1100111 '
b10101 7
1Q
1O
1K
#245000
1%
1H
b10101 [
#250000
0%
0H
b10100000 '
b10110 7
0Q
0P
0O
0K
1J
#255000
1%
1H
b10110 [
#260000
0%
0H
b101 '
b10111 7
1Q
1O
0L
0J
#265000
1%
1H
b10111 [
#270000
0%
0H
b11000101 '
b11000 7
1K
1J
#275000
1%
1H
b11000 [
#280000
0%
0H
b101000 '
b11001 7
0Q
0O
1N
1L
0K
0J
#285000
1%
1H
b11001 [
#290000
0%
0H
b1000100 '
b11010 7
1O
0N
0L
1K
#295000
1%
1H
b11010 [
#300000
0%
0H
b1100010 '
b11011 7
1P
0O
1L
#305000
1%
1H
b11011 [
#310000
0%
0H
b1100110 '
b11100 7
1O
#315000
1%
1H
b11100 [
#320000
0%
0H
b11001100 '
b11101 7
0P
1N
0L
1J
#325000
1%
1H
b11101 [
#330000
0%
0H
b1110110 '
b11110 7
1P
0N
1M
1L
0J
#335000
1%
1H
b11110 [
#340000
0%
0H
b10010111 '
b11111 7
1Q
0L
0K
1J
#345000
1%
1H
b11111 [
#350000
0%
0H
b1111001 '
b100000 7
0P
0O
1N
1L
1K
0J
#355000
1%
1H
b100000 [
#360000
0%
0H
b1010110 '
b100001 7
0Q
1P
1O
0N
0L
#365000
1%
1H
b100001 [
#370000
0%
0H
b101000 '
b100010 7
0P
0O
1N
0M
1L
0K
#375000
1%
1H
b100010 [
#380000
0%
0H
b1001 '
b100011 7
1Q
0L
#385000
1%
1H
b100011 [
#390000
0%
0H
b11111111 '
b100100 7
1P
1O
1M
1L
1K
1J
#395000
1%
1H
b100100 [
#400000
0%
0H
b1000000 '
b100101 7
0Q
0P
0O
0N
0M
0L
0J
#405000
1%
1H
b100101 [
#410000
0%
0H
b11000 '
b100110 7
1N
1M
0K
#415000
1%
1H
b100110 [
#420000
0%
0H
b10000000 '
b100111 7
0N
0M
1J
#425000
1%
1H
b100111 [
#430000
0%
0H
b110011 '
b101000 7
1Q
1P
1M
1L
0J
#435000
1%
1H
b101000 [
#440000
0%
0H
b11100110 '
b101001 7
0Q
1O
0M
1K
1J
#445000
1%
1H
b101001 [
#450000
0%
0H
b11110000 '
b101010 7
0P
0O
1M
#455000
1%
1H
b101010 [
#460000
0%
0H
b11101001 '
b101011 7
1Q
1N
0M
#465000
1%
1H
b101011 [
#470000
0%
0H
b11101010 '
b101100 7
0Q
1P
#475000
1%
1H
b101100 [
#480000
0%
0H
b10000111 '
b101101 7
1Q
1O
0N
0L
0K
#485000
1%
1H
b101101 [
#490000
0%
0H
b11011101 '
b101110 7
0P
1N
1M
1K
#495000
1%
1H
b101110 [
#500000
0%
0H
b11101101 '
b101111 7
0M
1L
#505000
1%
1H
b101111 [
#510000
0%
0H
b10010101 '
b110000 7
0N
1M
0L
0K
#515000
1%
1H
b110000 [
#520000
0%
0H
b1111000 '
b110001 7
0Q
0O
1N
1L
1K
0J
#525000
1%
1H
b110001 [
#530000
0%
0H
b11010100 '
b110010 7
1O
0N
0L
1J
#535000
1%
1H
b110010 [
#540000
0%
0H
b11010011 '
b110011 7
1Q
1P
0O
#545000
1%
1H
b110011 [
#550000
0%
0H
b10111011 '
b110100 7
1N
1L
0K
#555000
1%
1H
b110100 [
#560000
0%
0H
b11110100 '
b110101 7
0Q
0P
1O
0N
1K
#565000
1%
1H
b110101 [
#570000
0%
0H
b1110111 '
b110110 7
1Q
1P
0J
#575000
1%
1H
b110110 [
#580000
0%
0H
b1010010 '
b110111 7
0Q
0O
0L
#585000
1%
1H
b110111 [
#590000
0%
0H
b11000011 '
b111000 7
1Q
0M
1J
#595000
1%
1H
b111000 [
#600000
0%
0H
b11000100 '
b111001 7
0Q
0P
1O
#605000
1%
1H
b111001 [
#610000
0%
0H
b10101010 '
b111010 7
1P
0O
1N
1L
0K
#615000
1%
1H
b111010 [
#620000
0%
0H
b10110101 '
b111011 7
1Q
0P
1O
0N
1M
#625000
1%
1H
b111011 [
#630000
0%
0H
b10010010 '
b111100 7
0Q
1P
0O
0L
#635000
1%
1H
b111100 [
#640000
0%
0H
b10011000 '
b111101 7
0P
1N
#645000
1%
1H
b111101 [
#650000
0%
0H
b11101110 '
b111110 7
1P
1O
0M
1L
1K
#655000
1%
1H
b111110 [
#660000
0%
0H
b0 '
b111111 7
0P
0O
0N
0L
0K
0J
#665000
1%
1H
b111111 [
b11 Z
#670000
0%
0H
b10101001 '
b1000000 7
1Q
1N
1L
1J
#675000
1%
1H
b11 Y
b0 [
#680000
0%
0H
bx '
b1000001 7
b1 6
bz '
zQ
zP
zO
zN
zM
zL
zK
zJ
#685000
1%
1H
b11111111 V
1W
b1 [
11
10
1/
1.
1-
1,
1+
1*
12
#690000
0%
0H
#695000
1%
1H
b1 :
b11100111 V
b10 [
0.
0-
#700000
0%
0H
#705000
1%
1H
b11100111 4
b10 :
b1010101 V
b11 [
00
1-
0,
0*
#710000
0%
0H
#715000
1%
1H
b1010101 4
b11 :
b1110101 V
b100 [
1,
#720000
0%
0H
#725000
1%
1H
b1110101 4
b100 :
b1100001 V
b101 [
0/
0-
#730000
0%
0H
#735000
1%
1H
b1100001 4
b101 :
b10010011 V
b110 [
10
1-
0,
0+
1*
#740000
0%
0H
#745000
1%
1H
b10010011 4
b110 :
b1100111 V
b111 [
1/
0-
1,
1+
0*
#750000
0%
0H
#755000
1%
1H
b1100111 4
b111 :
b101 V
b1000 [
00
0,
0+
#760000
0%
0H
#765000
1%
1H
b101 4
b1000 :
b1010110 V
b1001 [
01
10
1-
1+
#770000
0%
0H
#775000
1%
1H
b1010110 4
b1001 :
b1001 V
b1010 [
11
00
0/
1.
0-
0+
#780000
0%
0H
#785000
1%
1H
b1001 4
b1010 :
b1000000 V
b1011 [
01
0.
1+
#790000
0%
0H
#795000
1%
1H
b1000000 4
b1011 :
b10000000 V
b1100 [
0+
1*
#800000
0%
0H
#805000
1%
1H
b10000000 4
b1100 :
b1111000 V
b1101 [
1.
1-
1,
1+
0*
#810000
0%
0H
#815000
1%
1H
b1111000 4
b1101 :
b11010011 V
b1110 [
11
10
0.
0,
1*
#820000
0%
0H
#825000
1%
1H
b11010011 4
b1110 :
b11110100 V
b1111 [
01
00
1/
1,
#830000
0%
0H
#835000
1%
1H
b11110100 4
b1111 :
b1010010 V
b10000 [
10
0/
0,
0*
b0 Z
#840000
0%
0H
#845000
1%
1H
b1010010 4
b10000 :
b0 Y
0W
b0 [
0X
02
03
b10 Z
#850000
0%
0H
b11 (
1)
1U
1T
1S
0R
#855000
1%
1H
b11111111 4
b10 Y
1X
13
b11 Z
#860000
0%
0H
0)
b10 6
bz (
0U
zT
zS
zR
#865000
1%
1H
b11 Y
#870000
0%
0H
#875000
1%
1H
b11111111 V
1W
b1 [
11
1/
1.
1,
1*
12
#880000
0%
0H
#885000
1%
1H
b10001 :
b11100111 V
b10 [
0.
0-
#890000
0%
0H
#895000
1%
1H
b11100111 4
b10010 :
b1010101 V
b11 [
00
1-
0,
0*
#900000
0%
0H
#905000
1%
1H
b1010101 4
b10011 :
b1110101 V
b100 [
1,
#910000
0%
0H
#915000
1%
1H
b1110101 4
b10100 :
b1100001 V
b101 [
0/
0-
#920000
0%
0H
#925000
1%
1H
b1100001 4
b10101 :
b10010011 V
b110 [
10
1-
0,
0+
1*
#930000
0%
0H
#935000
1%
1H
b10010011 4
b10110 :
b1100111 V
b111 [
1/
0-
1,
1+
0*
#940000
0%
0H
#945000
1%
1H
b1100111 4
b10111 :
b101 V
b1000 [
00
0,
0+
#950000
0%
0H
#955000
1%
1H
b101 4
b11000 :
b1010110 V
b1001 [
01
10
1-
1+
#960000
0%
0H
#965000
1%
1H
b1010110 4
b11001 :
b1001 V
b1010 [
11
00
0/
1.
0-
0+
#970000
0%
0H
#975000
1%
1H
b1001 4
b11010 :
b1000000 V
b1011 [
01
0.
1+
#980000
0%
0H
#985000
1%
1H
b1000000 4
b11011 :
b10000000 V
b1100 [
0+
1*
#990000
0%
0H
#995000
1%
1H
b10000000 4
b11100 :
b1111000 V
b1101 [
1.
1-
1,
1+
0*
#1000000
0%
0H
#1005000
1%
1H
b1111000 4
b11101 :
b11010011 V
b1110 [
11
10
0.
0,
1*
#1010000
0%
0H
#1015000
1%
1H
b11010011 4
b11110 :
b11110100 V
b1111 [
01
00
1/
1,
#1020000
0%
0H
#1025000
1%
1H
b11110100 4
b11111 :
b1010010 V
b10000 [
10
0/
0,
0*
b0 Z
#1030000
0%
0H
#1035000
1%
1H
b1010010 4
b100000 :
b0 Y
0W
b0 [
0X
02
03
b10 Z
#1040000
0%
0H
b1 (
1)
b0 7
1U
1T
0S
0R
b1 Z
#1045000
1%
1H
b11111111 4
b1 Y
1X
13
#1050000
0%
0H
b11111111 '
bz (
0)
b1 7
1Q
1P
1O
1N
1M
1L
1K
1J
0U
zT
zS
zR
#1055000
1%
1H
b1 [
#1060000
0%
0H
b110110 '
b10 7
0Q
0N
0K
0J
#1065000
1%
1H
b10 [
#1070000
0%
0H
b11100111 '
b11 7
1Q
0M
1K
1J
#1075000
1%
1H
b11 [
#1080000
0%
0H
b11110000 '
b100 7
0Q
0P
0O
1M
#1085000
1%
1H
b100 [
#1090000
0%
0H
b1010101 '
b101 7
1Q
1O
0L
0J
#1095000
1%
1H
b101 [
#1100000
0%
0H
b110010 '
b110 7
0Q
1P
0O
1L
0K
#1105000
1%
1H
b110 [
#1110000
0%
0H
b1110101 '
b111 7
1Q
0P
1O
1K
#1115000
1%
1H
b111 [
#1120000
0%
0H
b1000010 '
b1000 7
0Q
1P
0O
0M
0L
#1125000
1%
1H
b1000 [
#1130000
0%
0H
b11000 '
b1001 7
0P
1N
1M
0K
#1135000
1%
1H
b1001 [
#1140000
0%
0H
b100000 '
b1010 7
0N
0M
1L
#1145000
1%
1H
b1010 [
#1150000
0%
0H
b1010111 '
b1011 7
1Q
1P
1O
1M
0L
1K
#1155000
1%
1H
b1011 [
#1160000
0%
0H
b110000 '
b1100 7
0Q
0P
0O
1L
0K
#1165000
1%
1H
b1100 [
#1170000
0%
0H
b11101011 '
b1101 7
1Q
1P
1N
0M
1K
1J
#1175000
1%
1H
b1101 [
#1180000
0%
0H
b10101111 '
b1110 7
1O
0K
#1185000
1%
1H
b1110 [
#1190000
0%
0H
b11101100 '
b1111 7
0Q
0P
1K
#1195000
1%
1H
b1111 [
#1200000
0%
0H
b10001 '
b10000 7
1Q
0O
0N
1M
0L
0K
0J
#1205000
1%
1H
b10000 [
#1210000
0%
0H
b1100001 '
b10001 7
0M
1L
1K
#1215000
1%
1H
b10001 [
#1220000
0%
0H
b1001001 '
b10010 7
1N
0L
#1225000
1%
1H
b10010 [
#1230000
0%
0H
b10010011 '
b10011 7
1P
0N
1M
0K
1J
#1235000
1%
1H
b10011 [
#1240000
0%
0H
b100010 '
b10100 7
0Q
0M
1L
0J
#1245000
1%
1H
b10100 [
#1250000
0%
0H
b1100111 '
b10101 7
1Q
1O
1K
#1255000
1%
1H
b10101 [
#1260000
0%
0H
b10100000 '
b10110 7
0Q
0P
0O
0K
1J
#1265000
1%
1H
b10110 [
#1270000
0%
0H
b101 '
b10111 7
1Q
1O
0L
0J
#1275000
1%
1H
b10111 [
#1280000
0%
0H
b11000101 '
b11000 7
1K
1J
#1285000
1%
1H
b11000 [
#1290000
0%
0H
b101000 '
b11001 7
0Q
0O
1N
1L
0K
0J
#1295000
1%
1H
b11001 [
#1300000
0%
0H
b1000100 '
b11010 7
1O
0N
0L
1K
#1305000
1%
1H
b11010 [
#1310000
0%
0H
b1100010 '
b11011 7
1P
0O
1L
#1315000
1%
1H
b11011 [
#1320000
0%
0H
b1100110 '
b11100 7
1O
#1325000
1%
1H
b11100 [
#1330000
0%
0H
b11001100 '
b11101 7
0P
1N
0L
1J
#1335000
1%
1H
b11101 [
#1340000
0%
0H
b1110110 '
b11110 7
1P
0N
1M
1L
0J
#1345000
1%
1H
b11110 [
#1350000
0%
0H
b10010111 '
b11111 7
1Q
0L
0K
1J
#1355000
1%
1H
b11111 [
#1360000
0%
0H
b1111001 '
b100000 7
0P
0O
1N
1L
1K
0J
#1365000
1%
1H
b100000 [
#1370000
0%
0H
b1010110 '
b100001 7
0Q
1P
1O
0N
0L
#1375000
1%
1H
b100001 [
#1380000
0%
0H
b101000 '
b100010 7
0P
0O
1N
0M
1L
0K
#1385000
1%
1H
b100010 [
#1390000
0%
0H
b1001 '
b100011 7
1Q
0L
#1395000
1%
1H
b100011 [
#1400000
0%
0H
b11111111 '
b100100 7
1P
1O
1M
1L
1K
1J
#1405000
1%
1H
b100100 [
#1410000
0%
0H
b1000000 '
b100101 7
0Q
0P
0O
0N
0M
0L
0J
#1415000
1%
1H
b100101 [
#1420000
0%
0H
b11000 '
b100110 7
1N
1M
0K
#1425000
1%
1H
b100110 [
#1430000
0%
0H
b10000000 '
b100111 7
0N
0M
1J
#1435000
1%
1H
b100111 [
#1440000
0%
0H
b110011 '
b101000 7
1Q
1P
1M
1L
0J
#1445000
1%
1H
b101000 [
#1450000
0%
0H
b11100110 '
b101001 7
0Q
1O
0M
1K
1J
#1455000
1%
1H
b101001 [
#1460000
0%
0H
b11110000 '
b101010 7
0P
0O
1M
#1465000
1%
1H
b101010 [
#1470000
0%
0H
b11101001 '
b101011 7
1Q
1N
0M
#1475000
1%
1H
b101011 [
#1480000
0%
0H
b11101010 '
b101100 7
0Q
1P
#1485000
1%
1H
b101100 [
#1490000
0%
0H
b10000111 '
b101101 7
1Q
1O
0N
0L
0K
#1495000
1%
1H
b101101 [
#1500000
0%
0H
b11011101 '
b101110 7
0P
1N
1M
1K
#1505000
1%
1H
b101110 [
#1510000
0%
0H
b11101101 '
b101111 7
0M
1L
#1515000
1%
1H
b101111 [
#1520000
0%
0H
b10010101 '
b110000 7
0N
1M
0L
0K
#1525000
1%
1H
b110000 [
#1530000
0%
0H
b1111000 '
b110001 7
0Q
0O
1N
1L
1K
0J
#1535000
1%
1H
b110001 [
#1540000
0%
0H
b11010100 '
b110010 7
1O
0N
0L
1J
#1545000
1%
1H
b110010 [
#1550000
0%
0H
b11010011 '
b110011 7
1Q
1P
0O
#1555000
1%
1H
b110011 [
#1560000
0%
0H
b10111011 '
b110100 7
1N
1L
0K
